{".class":"MypyFile","_fullname":"digital_image_processing.filters.bilateral_filter","future_import_flags":[],"is_partial_stub_package":false,"is_stub":false,"names":{".class":"SymbolTable","__annotations__":{".class":"SymbolTableNode","kind":"Gdef","node":{".class":"Var","flags":["is_ready"],"fullname":"digital_image_processing.filters.bilateral_filter.__annotations__","name":"__annotations__","type":{".class":"Instance","args":["builtins.str",{".class":"AnyType","missing_import_name":null,"source_any":null,"type_of_any":6}],"extra_attrs":null,"type_ref":"builtins.dict"}}},"__doc__":{".class":"SymbolTableNode","kind":"Gdef","node":{".class":"Var","flags":["is_ready"],"fullname":"digital_image_processing.filters.bilateral_filter.__doc__","name":"__doc__","type":"builtins.str"}},"__file__":{".class":"SymbolTableNode","kind":"Gdef","node":{".class":"Var","flags":["is_ready"],"fullname":"digital_image_processing.filters.bilateral_filter.__file__","name":"__file__","type":"builtins.str"}},"__name__":{".class":"SymbolTableNode","kind":"Gdef","node":{".class":"Var","flags":["is_ready"],"fullname":"digital_image_processing.filters.bilateral_filter.__name__","name":"__name__","type":"builtins.str"}},"__package__":{".class":"SymbolTableNode","kind":"Gdef","node":{".class":"Var","flags":["is_ready"],"fullname":"digital_image_processing.filters.bilateral_filter.__package__","name":"__package__","type":"builtins.str"}},"__spec__":{".class":"SymbolTableNode","kind":"Gdef","node":{".class":"Var","flags":["is_ready"],"fullname":"digital_image_processing.filters.bilateral_filter.__spec__","name":"__spec__","type":"importlib.machinery.ModuleSpec"}},"bilateral_filter":{".class":"SymbolTableNode","kind":"Gdef","node":{".class":"FuncDef","abstract_status":0,"arg_kinds":[0,0,0,0],"arg_names":["img","spatial_variance","intensity_variance","kernel_size"],"dataclass_transform_spec":null,"flags":[],"fullname":"digital_image_processing.filters.bilateral_filter.bilateral_filter","name":"bilateral_filter","type":{".class":"CallableType","arg_kinds":[0,0,0,0],"arg_names":["img","spatial_variance","intensity_variance","kernel_size"],"arg_types":[{".class":"AnyType","missing_import_name":"digital_image_processing.filters.bilateral_filter.np","source_any":null,"type_of_any":3},"builtins.float","builtins.float","builtins.int"],"bound_args":[],"def_extras":{"first_arg":null},"fallback":"builtins.function","from_concatenate":false,"implicit":false,"imprecise_arg_kinds":false,"is_ellipsis_args":false,"name":"bilateral_filter","ret_type":{".class":"AnyType","missing_import_name":"digital_image_processing.filters.bilateral_filter.np","source_any":null,"type_of_any":3},"type_guard":null,"type_is":null,"unpack_kwargs":false,"variables":[]}}},"cv2":{".class":"SymbolTableNode","kind":"Gdef","node":{".class":"Var","flags":["is_suppressed_import","is_ready","is_inferred"],"fullname":"digital_image_processing.filters.bilateral_filter.cv2","name":"cv2","type":{".class":"AnyType","missing_import_name":"digital_image_processing.filters.bilateral_filter.cv2","source_any":null,"type_of_any":3}}},"filename":{".class":"SymbolTableNode","kind":"Gdef","node":{".class":"Var","flags":["is_inferred","has_explicit_value"],"fullname":"digital_image_processing.filters.bilateral_filter.filename","name":"filename","type":{".class":"AnyType","missing_import_name":null,"source_any":null,"type_of_any":4}}},"get_gauss_kernel":{".class":"SymbolTableNode","kind":"Gdef","node":{".class":"FuncDef","abstract_status":0,"arg_kinds":[0,0],"arg_names":["kernel_size","spatial_variance"],"dataclass_transform_spec":null,"flags":[],"fullname":"digital_image_processing.filters.bilateral_filter.get_gauss_kernel","name":"get_gauss_kernel","type":{".class":"CallableType","arg_kinds":[0,0],"arg_names":["kernel_size","spatial_variance"],"arg_types":["builtins.int","builtins.float"],"bound_args":[],"def_extras":{"first_arg":null},"fallback":"builtins.function","from_concatenate":false,"implicit":false,"imprecise_arg_kinds":false,"is_ellipsis_args":false,"name":"get_gauss_kernel","ret_type":{".class":"AnyType","missing_import_name":"digital_image_processing.filters.bilateral_filter.np","source_any":null,"type_of_any":3},"type_guard":null,"type_is":null,"unpack_kwargs":false,"variables":[]}}},"get_slice":{".class":"SymbolTableNode","kind":"Gdef","node":{".class":"FuncDef","abstract_status":0,"arg_kinds":[0,0,0,0],"arg_names":["img","x","y","kernel_size"],"dataclass_transform_spec":null,"flags":[],"fullname":"digital_image_processing.filters.bilateral_filter.get_slice","name":"get_slice","type":{".class":"CallableType","arg_kinds":[0,0,0,0],"arg_names":["img","x","y","kernel_size"],"arg_types":[{".class":"AnyType","missing_import_name":"digital_image_processing.filters.bilateral_filter.np","source_any":null,"type_of_any":3},"builtins.int","builtins.int","builtins.int"],"bound_args":[],"def_extras":{"first_arg":null},"fallback":"builtins.function","from_concatenate":false,"implicit":false,"imprecise_arg_kinds":false,"is_ellipsis_args":false,"name":"get_slice","ret_type":{".class":"AnyType","missing_import_name":"digital_image_processing.filters.bilateral_filter.np","source_any":null,"type_of_any":3},"type_guard":null,"type_is":null,"unpack_kwargs":false,"variables":[]}}},"img":{".class":"SymbolTableNode","kind":"Gdef","node":{".class":"Var","flags":["is_inferred","has_explicit_value"],"fullname":"digital_image_processing.filters.bilateral_filter.img","name":"img","type":{".class":"AnyType","missing_import_name":"digital_image_processing.filters.bilateral_filter.cv2","source_any":{".class":"AnyType","missing_import_name":"digital_image_processing.filters.bilateral_filter.cv2","source_any":null,"type_of_any":3},"type_of_any":7}}},"intensity_variance":{".class":"SymbolTableNode","kind":"Gdef","node":{".class":"Var","flags":["is_inferred","has_explicit_value"],"fullname":"digital_image_processing.filters.bilateral_filter.intensity_variance","name":"intensity_variance","type":{".class":"AnyType","missing_import_name":null,"source_any":null,"type_of_any":4}}},"kernel_size":{".class":"SymbolTableNode","kind":"Gdef","node":{".class":"Var","flags":["is_inferred","has_explicit_value"],"fullname":"digital_image_processing.filters.bilateral_filter.kernel_size","name":"kernel_size","type":{".class":"AnyType","missing_import_name":null,"source_any":null,"type_of_any":4}}},"math":{".class":"SymbolTableNode","cross_ref":"math","kind":"Gdef"},"np":{".class":"SymbolTableNode","kind":"Gdef","node":{".class":"Var","flags":["is_suppressed_import","is_ready","is_inferred"],"fullname":"digital_image_processing.filters.bilateral_filter.np","name":"np","type":{".class":"AnyType","missing_import_name":"digital_image_processing.filters.bilateral_filter.np","source_any":null,"type_of_any":3}}},"out":{".class":"SymbolTableNode","kind":"Gdef","node":{".class":"Var","flags":["is_inferred","has_explicit_value"],"fullname":"digital_image_processing.filters.bilateral_filter.out","name":"out","type":{".class":"AnyType","missing_import_name":"digital_image_processing.filters.bilateral_filter.cv2","source_any":{".class":"AnyType","missing_import_name":"digital_image_processing.filters.bilateral_filter.cv2","source_any":null,"type_of_any":3},"type_of_any":7}}},"parse_args":{".class":"SymbolTableNode","kind":"Gdef","node":{".class":"FuncDef","abstract_status":0,"arg_kinds":[0],"arg_names":["args"],"dataclass_transform_spec":null,"flags":[],"fullname":"digital_image_processing.filters.bilateral_filter.parse_args","name":"parse_args","type":{".class":"CallableType","arg_kinds":[0],"arg_names":["args"],"arg_types":[{".class":"Instance","args":[{".class":"AnyType","missing_import_name":null,"source_any":null,"type_of_any":4}],"extra_attrs":null,"type_ref":"builtins.list"}],"bound_args":[],"def_extras":{"first_arg":null},"fallback":"builtins.function","from_concatenate":false,"implicit":false,"imprecise_arg_kinds":false,"is_ellipsis_args":false,"name":"parse_args","ret_type":{".class":"Instance","args":[{".class":"AnyType","missing_import_name":null,"source_any":null,"type_of_any":4}],"extra_attrs":null,"type_ref":"builtins.tuple"},"type_guard":null,"type_is":null,"unpack_kwargs":false,"variables":[]}}},"spatial_variance":{".class":"SymbolTableNode","kind":"Gdef","node":{".class":"Var","flags":["is_inferred","has_explicit_value"],"fullname":"digital_image_processing.filters.bilateral_filter.spatial_variance","name":"spatial_variance","type":{".class":"AnyType","missing_import_name":null,"source_any":null,"type_of_any":4}}},"sys":{".class":"SymbolTableNode","cross_ref":"sys","kind":"Gdef"},"vec_gaussian":{".class":"SymbolTableNode","kind":"Gdef","node":{".class":"FuncDef","abstract_status":0,"arg_kinds":[0,0],"arg_names":["img","variance"],"dataclass_transform_spec":null,"flags":[],"fullname":"digital_image_processing.filters.bilateral_filter.vec_gaussian","name":"vec_gaussian","type":{".class":"CallableType","arg_kinds":[0,0],"arg_names":["img","variance"],"arg_types":[{".class":"AnyType","missing_import_name":"digital_image_processing.filters.bilateral_filter.np","source_any":null,"type_of_any":3},"builtins.float"],"bound_args":[],"def_extras":{"first_arg":null},"fallback":"builtins.function","from_concatenate":false,"implicit":false,"imprecise_arg_kinds":false,"is_ellipsis_args":false,"name":"vec_gaussian","ret_type":{".class":"AnyType","missing_import_name":"digital_image_processing.filters.bilateral_filter.np","source_any":null,"type_of_any":3},"type_guard":null,"type_is":null,"unpack_kwargs":false,"variables":[]}}}},"path":"domains\\python-master\\Python-master\\digital_image_processing\\filters\\bilateral_filter.py"}
