{".class":"MypyFile","_fullname":"maths.gaussian","future_import_flags":[],"is_partial_stub_package":false,"is_stub":false,"names":{".class":"SymbolTable","__annotations__":{".class":"SymbolTableNode","kind":"Gdef","node":{".class":"Var","flags":["is_ready"],"fullname":"maths.gaussian.__annotations__","name":"__annotations__","type":{".class":"Instance","args":["builtins.str",{".class":"AnyType","missing_import_name":null,"source_any":null,"type_of_any":6}],"extra_attrs":null,"type_ref":"builtins.dict"}}},"__doc__":{".class":"SymbolTableNode","kind":"Gdef","node":{".class":"Var","flags":["is_ready"],"fullname":"maths.gaussian.__doc__","name":"__doc__","type":"builtins.str"}},"__file__":{".class":"SymbolTableNode","kind":"Gdef","node":{".class":"Var","flags":["is_ready"],"fullname":"maths.gaussian.__file__","name":"__file__","type":"builtins.str"}},"__name__":{".class":"SymbolTableNode","kind":"Gdef","node":{".class":"Var","flags":["is_ready"],"fullname":"maths.gaussian.__name__","name":"__name__","type":"builtins.str"}},"__package__":{".class":"SymbolTableNode","kind":"Gdef","node":{".class":"Var","flags":["is_ready"],"fullname":"maths.gaussian.__package__","name":"__package__","type":"builtins.str"}},"__spec__":{".class":"SymbolTableNode","kind":"Gdef","node":{".class":"Var","flags":["is_ready"],"fullname":"maths.gaussian.__spec__","name":"__spec__","type":"importlib.machinery.ModuleSpec"}},"doctest":{".class":"SymbolTableNode","cross_ref":"doctest","kind":"Gdef"},"exp":{".class":"SymbolTableNode","kind":"Gdef","node":{".class":"Var","flags":["is_suppressed_import","is_ready","is_inferred"],"fullname":"maths.gaussian.exp","name":"exp","type":{".class":"AnyType","missing_import_name":"maths.gaussian.exp","source_any":null,"type_of_any":3}}},"gaussian":{".class":"SymbolTableNode","kind":"Gdef","node":{".class":"FuncDef","abstract_status":0,"arg_kinds":[0,1,1],"arg_names":["x","mu","sigma"],"dataclass_transform_spec":null,"flags":[],"fullname":"maths.gaussian.gaussian","name":"gaussian","type":{".class":"CallableType","arg_kinds":[0,1,1],"arg_names":["x","mu","sigma"],"arg_types":[{".class":"AnyType","missing_import_name":null,"source_any":null,"type_of_any":1},"builtins.float","builtins.float"],"bound_args":[],"def_extras":{"first_arg":null},"fallback":"builtins.function","from_concatenate":false,"implicit":false,"imprecise_arg_kinds":false,"is_ellipsis_args":false,"name":"gaussian","ret_type":"builtins.float","type_guard":null,"type_is":null,"unpack_kwargs":false,"variables":[]}}},"pi":{".class":"SymbolTableNode","kind":"Gdef","node":{".class":"Var","flags":["is_suppressed_import","is_ready","is_inferred"],"fullname":"maths.gaussian.pi","name":"pi","type":{".class":"AnyType","missing_import_name":"maths.gaussian.pi","source_any":null,"type_of_any":3}}},"sqrt":{".class":"SymbolTableNode","kind":"Gdef","node":{".class":"Var","flags":["is_suppressed_import","is_ready","is_inferred"],"fullname":"maths.gaussian.sqrt","name":"sqrt","type":{".class":"AnyType","missing_import_name":"maths.gaussian.sqrt","source_any":null,"type_of_any":3}}}},"path":"domains\\python-master\\Python-master\\maths\\gaussian.py"}