{".class":"MypyFile","_fullname":"strings.min_cost_string_conversion","future_import_flags":[],"is_partial_stub_package":false,"is_stub":false,"names":{".class":"SymbolTable","_":{".class":"SymbolTableNode","kind":"Gdef","node":{".class":"Var","flags":["is_inferred","has_explicit_value"],"fullname":"strings.min_cost_string_conversion._","name":"_","type":{".class":"Instance","args":[{".class":"Instance","args":["builtins.int"],"extra_attrs":null,"type_ref":"builtins.list"}],"extra_attrs":null,"type_ref":"builtins.list"}}},"__annotations__":{".class":"SymbolTableNode","kind":"Gdef","node":{".class":"Var","flags":["is_ready"],"fullname":"strings.min_cost_string_conversion.__annotations__","name":"__annotations__","type":{".class":"Instance","args":["builtins.str",{".class":"AnyType","missing_import_name":null,"source_any":null,"type_of_any":6}],"extra_attrs":null,"type_ref":"builtins.dict"}}},"__doc__":{".class":"SymbolTableNode","kind":"Gdef","node":{".class":"Var","flags":["is_ready"],"fullname":"strings.min_cost_string_conversion.__doc__","name":"__doc__","type":"builtins.str"}},"__file__":{".class":"SymbolTableNode","kind":"Gdef","node":{".class":"Var","flags":["is_ready"],"fullname":"strings.min_cost_string_conversion.__file__","name":"__file__","type":"builtins.str"}},"__name__":{".class":"SymbolTableNode","kind":"Gdef","node":{".class":"Var","flags":["is_ready"],"fullname":"strings.min_cost_string_conversion.__name__","name":"__name__","type":"builtins.str"}},"__package__":{".class":"SymbolTableNode","kind":"Gdef","node":{".class":"Var","flags":["is_ready"],"fullname":"strings.min_cost_string_conversion.__package__","name":"__package__","type":"builtins.str"}},"__spec__":{".class":"SymbolTableNode","kind":"Gdef","node":{".class":"Var","flags":["is_ready"],"fullname":"strings.min_cost_string_conversion.__spec__","name":"__spec__","type":"importlib.machinery.ModuleSpec"}},"assemble_transformation":{".class":"SymbolTableNode","kind":"Gdef","node":{".class":"FuncDef","abstract_status":0,"arg_kinds":[0,0,0],"arg_names":["ops","i","j"],"dataclass_transform_spec":null,"flags":[],"fullname":"strings.min_cost_string_conversion.assemble_transformation","name":"assemble_transformation","type":{".class":"CallableType","arg_kinds":[0,0,0],"arg_names":["ops","i","j"],"arg_types":[{".class":"Instance","args":[{".class":"Instance","args":["builtins.str"],"extra_attrs":null,"type_ref":"builtins.list"}],"extra_attrs":null,"type_ref":"builtins.list"},"builtins.int","builtins.int"],"bound_args":[],"def_extras":{"first_arg":null},"fallback":"builtins.function","from_concatenate":false,"implicit":false,"imprecise_arg_kinds":false,"is_ellipsis_args":false,"name":"assemble_transformation","ret_type":{".class":"Instance","args":["builtins.str"],"extra_attrs":null,"type_ref":"builtins.list"},"type_guard":null,"type_is":null,"unpack_kwargs":false,"variables":[]}}},"compute_transform_tables":{".class":"SymbolTableNode","kind":"Gdef","node":{".class":"FuncDef","abstract_status":0,"arg_kinds":[0,0,0,0,0,0],"arg_names":["source_string","destination_string","copy_cost","replace_cost","delete_cost","insert_cost"],"dataclass_transform_spec":null,"flags":[],"fullname":"strings.min_cost_string_conversion.compute_transform_tables","name":"compute_transform_tables","type":{".class":"CallableType","arg_kinds":[0,0,0,0,0,0],"arg_names":["source_string","destination_string","copy_cost","replace_cost","delete_cost","insert_cost"],"arg_types":["builtins.str","builtins.str","builtins.int","builtins.int","builtins.int","builtins.int"],"bound_args":[],"def_extras":{"first_arg":null},"fallback":"builtins.function","from_concatenate":false,"implicit":false,"imprecise_arg_kinds":false,"is_ellipsis_args":false,"name":"compute_transform_tables","ret_type":{".class":"TupleType","implicit":false,"items":[{".class":"Instance","args":[{".class":"Instance","args":["builtins.int"],"extra_attrs":null,"type_ref":"builtins.list"}],"extra_attrs":null,"type_ref":"builtins.list"},{".class":"Instance","args":[{".class":"Instance","args":["builtins.str"],"extra_attrs":null,"type_ref":"builtins.list"}],"extra_attrs":null,"type_ref":"builtins.list"}],"partial_fallback":{".class":"Instance","args":[{".class":"AnyType","missing_import_name":null,"source_any":null,"type_of_any":6}],"extra_attrs":null,"type_ref":"builtins.tuple"}},"type_guard":null,"type_is":null,"unpack_kwargs":false,"variables":[]}}},"cost":{".class":"SymbolTableNode","kind":"Gdef","node":{".class":"Var","flags":["is_ready","is_inferred","has_explicit_value"],"fullname":"strings.min_cost_string_conversion.cost","name":"cost","type":"builtins.int"}},"file":{".class":"SymbolTableNode","kind":"Gdef","node":{".class":"Var","flags":["is_inferred"],"fullname":"strings.min_cost_string_conversion.file","name":"file","type":"io.TextIOWrapper"}},"i":{".class":"SymbolTableNode","kind":"Gdef","node":{".class":"Var","flags":["is_ready","is_inferred","has_explicit_value"],"fullname":"strings.min_cost_string_conversion.i","name":"i","type":"builtins.int"}},"m":{".class":"SymbolTableNode","kind":"Gdef","node":{".class":"Var","flags":["is_inferred","has_explicit_value"],"fullname":"strings.min_cost_string_conversion.m","name":"m","type":"builtins.int"}},"n":{".class":"SymbolTableNode","kind":"Gdef","node":{".class":"Var","flags":["is_inferred","has_explicit_value"],"fullname":"strings.min_cost_string_conversion.n","name":"n","type":"builtins.int"}},"op":{".class":"SymbolTableNode","kind":"Gdef","node":{".class":"Var","flags":["is_inferred"],"fullname":"strings.min_cost_string_conversion.op","name":"op","type":"builtins.str"}},"operations":{".class":"SymbolTableNode","kind":"Gdef","node":{".class":"Var","flags":["is_inferred","has_explicit_value"],"fullname":"strings.min_cost_string_conversion.operations","name":"operations","type":{".class":"Instance","args":[{".class":"Instance","args":["builtins.str"],"extra_attrs":null,"type_ref":"builtins.list"}],"extra_attrs":null,"type_ref":"builtins.list"}}},"sequence":{".class":"SymbolTableNode","kind":"Gdef","node":{".class":"Var","flags":["is_inferred","has_explicit_value"],"fullname":"strings.min_cost_string_conversion.sequence","name":"sequence","type":{".class":"Instance","args":["builtins.str"],"extra_attrs":null,"type_ref":"builtins.list"}}},"string":{".class":"SymbolTableNode","kind":"Gdef","node":{".class":"Var","flags":["is_inferred","has_explicit_value"],"fullname":"strings.min_cost_string_conversion.string","name":"string","type":{".class":"Instance","args":["builtins.str"],"extra_attrs":null,"type_ref":"builtins.list"}}}},"path":"domains\\python-master\\Python-master\\strings\\min_cost_string_conversion.py"}