{".class":"MypyFile","_fullname":"conversions.prefix_conversions_string","future_import_flags":["annotations"],"is_partial_stub_package":false,"is_stub":false,"names":{".class":"SymbolTable","BinaryUnit":{".class":"SymbolTableNode","kind":"Gdef","node":{".class":"TypeInfo","_promote":[],"abstract_attributes":[],"alt_promote":null,"bases":["enum.Enum"],"dataclass_transform_spec":null,"declared_metaclass":null,"defn":{".class":"ClassDef","fullname":"conversions.prefix_conversions_string.BinaryUnit","name":"BinaryUnit","type_vars":[]},"deletable_attributes":[],"flags":["is_enum"],"fullname":"conversions.prefix_conversions_string.BinaryUnit","has_param_spec_type":false,"metaclass_type":"enum.EnumMeta","metadata":{},"module_name":"conversions.prefix_conversions_string","mro":["conversions.prefix_conversions_string.BinaryUnit","enum.Enum","builtins.object"],"names":{".class":"SymbolTable","exa":{".class":"SymbolTableNode","kind":"Mdef","node":{".class":"Var","flags":["is_initialized_in_class","is_final","is_ready","is_inferred","has_explicit_value"],"fullname":"conversions.prefix_conversions_string.BinaryUnit.exa","name":"exa","type":{".class":"Instance","args":[],"extra_attrs":null,"last_known_value":{".class":"LiteralType","fallback":"builtins.int","value":60},"type_ref":"builtins.int"}}},"giga":{".class":"SymbolTableNode","kind":"Mdef","node":{".class":"Var","flags":["is_initialized_in_class","is_final","is_ready","is_inferred","has_explicit_value"],"fullname":"conversions.prefix_conversions_string.BinaryUnit.giga","name":"giga","type":{".class":"Instance","args":[],"extra_attrs":null,"last_known_value":{".class":"LiteralType","fallback":"builtins.int","value":30},"type_ref":"builtins.int"}}},"kilo":{".class":"SymbolTableNode","kind":"Mdef","node":{".class":"Var","flags":["is_initialized_in_class","is_final","is_ready","is_inferred","has_explicit_value"],"fullname":"conversions.prefix_conversions_string.BinaryUnit.kilo","name":"kilo","type":{".class":"Instance","args":[],"extra_attrs":null,"last_known_value":{".class":"LiteralType","fallback":"builtins.int","value":10},"type_ref":"builtins.int"}}},"mega":{".class":"SymbolTableNode","kind":"Mdef","node":{".class":"Var","flags":["is_initialized_in_class","is_final","is_ready","is_inferred","has_explicit_value"],"fullname":"conversions.prefix_conversions_string.BinaryUnit.mega","name":"mega","type":{".class":"Instance","args":[],"extra_attrs":null,"last_known_value":{".class":"LiteralType","fallback":"builtins.int","value":20},"type_ref":"builtins.int"}}},"peta":{".class":"SymbolTableNode","kind":"Mdef","node":{".class":"Var","flags":["is_initialized_in_class","is_final","is_ready","is_inferred","has_explicit_value"],"fullname":"conversions.prefix_conversions_string.BinaryUnit.peta","name":"peta","type":{".class":"Instance","args":[],"extra_attrs":null,"last_known_value":{".class":"LiteralType","fallback":"builtins.int","value":50},"type_ref":"builtins.int"}}},"tera":{".class":"SymbolTableNode","kind":"Mdef","node":{".class":"Var","flags":["is_initialized_in_class","is_final","is_ready","is_inferred","has_explicit_value"],"fullname":"conversions.prefix_conversions_string.BinaryUnit.tera","name":"tera","type":{".class":"Instance","args":[],"extra_attrs":null,"last_known_value":{".class":"LiteralType","fallback":"builtins.int","value":40},"type_ref":"builtins.int"}}},"yotta":{".class":"SymbolTableNode","kind":"Mdef","node":{".class":"Var","flags":["is_initialized_in_class","is_final","is_ready","is_inferred","has_explicit_value"],"fullname":"conversions.prefix_conversions_string.BinaryUnit.yotta","name":"yotta","type":{".class":"Instance","args":[],"extra_attrs":null,"last_known_value":{".class":"LiteralType","fallback":"builtins.int","value":80},"type_ref":"builtins.int"}}},"zetta":{".class":"SymbolTableNode","kind":"Mdef","node":{".class":"Var","flags":["is_initialized_in_class","is_final","is_ready","is_inferred","has_explicit_value"],"fullname":"conversions.prefix_conversions_string.BinaryUnit.zetta","name":"zetta","type":{".class":"Instance","args":[],"extra_attrs":null,"last_known_value":{".class":"LiteralType","fallback":"builtins.int","value":70},"type_ref":"builtins.int"}}}},"self_type":{".class":"TypeVarType","default":{".class":"AnyType","missing_import_name":null,"source_any":null,"type_of_any":4},"fullname":"conversions.prefix_conversions_string.BinaryUnit.Self","id":0,"name":"Self","namespace":"","upper_bound":"conversions.prefix_conversions_string.BinaryUnit","values":[],"variance":0},"slots":null,"tuple_type":null,"type_vars":[],"typeddict_type":null}},"Enum":{".class":"SymbolTableNode","cross_ref":"enum.Enum","kind":"Gdef"},"SIUnit":{".class":"SymbolTableNode","kind":"Gdef","node":{".class":"TypeInfo","_promote":[],"abstract_attributes":[],"alt_promote":null,"bases":["enum.Enum"],"dataclass_transform_spec":null,"declared_metaclass":null,"defn":{".class":"ClassDef","fullname":"conversions.prefix_conversions_string.SIUnit","name":"SIUnit","type_vars":[]},"deletable_attributes":[],"flags":["is_enum"],"fullname":"conversions.prefix_conversions_string.SIUnit","has_param_spec_type":false,"metaclass_type":"enum.EnumMeta","metadata":{},"module_name":"conversions.prefix_conversions_string","mro":["conversions.prefix_conversions_string.SIUnit","enum.Enum","builtins.object"],"names":{".class":"SymbolTable","atto":{".class":"SymbolTableNode","kind":"Mdef","node":{".class":"Var","flags":["is_initialized_in_class","is_final","is_ready","is_inferred","has_explicit_value"],"fullname":"conversions.prefix_conversions_string.SIUnit.atto","name":"atto","type":{".class":"Instance","args":[],"extra_attrs":null,"last_known_value":{".class":"LiteralType","fallback":"builtins.int","value":-18},"type_ref":"builtins.int"}}},"centi":{".class":"SymbolTableNode","kind":"Mdef","node":{".class":"Var","flags":["is_initialized_in_class","is_final","is_ready","is_inferred","has_explicit_value"],"fullname":"conversions.prefix_conversions_string.SIUnit.centi","name":"centi","type":{".class":"Instance","args":[],"extra_attrs":null,"last_known_value":{".class":"LiteralType","fallback":"builtins.int","value":-2},"type_ref":"builtins.int"}}},"deca":{".class":"SymbolTableNode","kind":"Mdef","node":{".class":"Var","flags":["is_initialized_in_class","is_final","is_ready","is_inferred","has_explicit_value"],"fullname":"conversions.prefix_conversions_string.SIUnit.deca","name":"deca","type":{".class":"Instance","args":[],"extra_attrs":null,"last_known_value":{".class":"LiteralType","fallback":"builtins.int","value":1},"type_ref":"builtins.int"}}},"deci":{".class":"SymbolTableNode","kind":"Mdef","node":{".class":"Var","flags":["is_initialized_in_class","is_final","is_ready","is_inferred","has_explicit_value"],"fullname":"conversions.prefix_conversions_string.SIUnit.deci","name":"deci","type":{".class":"Instance","args":[],"extra_attrs":null,"last_known_value":{".class":"LiteralType","fallback":"builtins.int","value":-1},"type_ref":"builtins.int"}}},"exa":{".class":"SymbolTableNode","kind":"Mdef","node":{".class":"Var","flags":["is_initialized_in_class","is_final","is_ready","is_inferred","has_explicit_value"],"fullname":"conversions.prefix_conversions_string.SIUnit.exa","name":"exa","type":{".class":"Instance","args":[],"extra_attrs":null,"last_known_value":{".class":"LiteralType","fallback":"builtins.int","value":18},"type_ref":"builtins.int"}}},"femto":{".class":"SymbolTableNode","kind":"Mdef","node":{".class":"Var","flags":["is_initialized_in_class","is_final","is_ready","is_inferred","has_explicit_value"],"fullname":"conversions.prefix_conversions_string.SIUnit.femto","name":"femto","type":{".class":"Instance","args":[],"extra_attrs":null,"last_known_value":{".class":"LiteralType","fallback":"builtins.int","value":-15},"type_ref":"builtins.int"}}},"get_negative":{".class":"SymbolTableNode","kind":"Mdef","node":{".class":"Decorator","func":{".class":"FuncDef","abstract_status":0,"arg_kinds":[0],"arg_names":["cls"],"dataclass_transform_spec":null,"flags":["is_class","is_decorated"],"fullname":"conversions.prefix_conversions_string.SIUnit.get_negative","name":"get_negative","type":{".class":"CallableType","arg_kinds":[0],"arg_names":["cls"],"arg_types":[{".class":"TypeType","item":"conversions.prefix_conversions_string.SIUnit"}],"bound_args":[],"def_extras":{"first_arg":"cls"},"fallback":"builtins.function","from_concatenate":false,"implicit":false,"imprecise_arg_kinds":false,"is_ellipsis_args":false,"name":"get_negative of SIUnit","ret_type":{".class":"Instance","args":[{".class":"AnyType","missing_import_name":null,"source_any":null,"type_of_any":4},{".class":"AnyType","missing_import_name":null,"source_any":null,"type_of_any":4}],"extra_attrs":null,"type_ref":"builtins.dict"},"type_guard":null,"type_is":null,"unpack_kwargs":false,"variables":[]}},"is_overload":false,"var":{".class":"Var","flags":["is_initialized_in_class","is_classmethod","is_ready","is_inferred"],"fullname":"conversions.prefix_conversions_string.SIUnit.get_negative","name":"get_negative","type":{".class":"CallableType","arg_kinds":[0],"arg_names":["cls"],"arg_types":[{".class":"TypeType","item":"conversions.prefix_conversions_string.SIUnit"}],"bound_args":[],"def_extras":{"first_arg":"cls"},"fallback":"builtins.function","from_concatenate":false,"implicit":false,"imprecise_arg_kinds":false,"is_ellipsis_args":false,"name":"get_negative of SIUnit","ret_type":{".class":"Instance","args":[{".class":"AnyType","missing_import_name":null,"source_any":null,"type_of_any":4},{".class":"AnyType","missing_import_name":null,"source_any":null,"type_of_any":4}],"extra_attrs":null,"type_ref":"builtins.dict"},"type_guard":null,"type_is":null,"unpack_kwargs":false,"variables":[]}}}},"get_positive":{".class":"SymbolTableNode","kind":"Mdef","node":{".class":"Decorator","func":{".class":"FuncDef","abstract_status":0,"arg_kinds":[0],"arg_names":["cls"],"dataclass_transform_spec":null,"flags":["is_class","is_decorated"],"fullname":"conversions.prefix_conversions_string.SIUnit.get_positive","name":"get_positive","type":{".class":"CallableType","arg_kinds":[0],"arg_names":["cls"],"arg_types":[{".class":"TypeType","item":"conversions.prefix_conversions_string.SIUnit"}],"bound_args":[],"def_extras":{"first_arg":"cls"},"fallback":"builtins.function","from_concatenate":false,"implicit":false,"imprecise_arg_kinds":false,"is_ellipsis_args":false,"name":"get_positive of SIUnit","ret_type":{".class":"Instance","args":[{".class":"AnyType","missing_import_name":null,"source_any":null,"type_of_any":4},{".class":"AnyType","missing_import_name":null,"source_any":null,"type_of_any":4}],"extra_attrs":null,"type_ref":"builtins.dict"},"type_guard":null,"type_is":null,"unpack_kwargs":false,"variables":[]}},"is_overload":false,"var":{".class":"Var","flags":["is_initialized_in_class","is_classmethod","is_ready","is_inferred"],"fullname":"conversions.prefix_conversions_string.SIUnit.get_positive","name":"get_positive","type":{".class":"CallableType","arg_kinds":[0],"arg_names":["cls"],"arg_types":[{".class":"TypeType","item":"conversions.prefix_conversions_string.SIUnit"}],"bound_args":[],"def_extras":{"first_arg":"cls"},"fallback":"builtins.function","from_concatenate":false,"implicit":false,"imprecise_arg_kinds":false,"is_ellipsis_args":false,"name":"get_positive of SIUnit","ret_type":{".class":"Instance","args":[{".class":"AnyType","missing_import_name":null,"source_any":null,"type_of_any":4},{".class":"AnyType","missing_import_name":null,"source_any":null,"type_of_any":4}],"extra_attrs":null,"type_ref":"builtins.dict"},"type_guard":null,"type_is":null,"unpack_kwargs":false,"variables":[]}}}},"giga":{".class":"SymbolTableNode","kind":"Mdef","node":{".class":"Var","flags":["is_initialized_in_class","is_final","is_ready","is_inferred","has_explicit_value"],"fullname":"conversions.prefix_conversions_string.SIUnit.giga","name":"giga","type":{".class":"Instance","args":[],"extra_attrs":null,"last_known_value":{".class":"LiteralType","fallback":"builtins.int","value":9},"type_ref":"builtins.int"}}},"hecto":{".class":"SymbolTableNode","kind":"Mdef","node":{".class":"Var","flags":["is_initialized_in_class","is_final","is_ready","is_inferred","has_explicit_value"],"fullname":"conversions.prefix_conversions_string.SIUnit.hecto","name":"hecto","type":{".class":"Instance","args":[],"extra_attrs":null,"last_known_value":{".class":"LiteralType","fallback":"builtins.int","value":2},"type_ref":"builtins.int"}}},"kilo":{".class":"SymbolTableNode","kind":"Mdef","node":{".class":"Var","flags":["is_initialized_in_class","is_final","is_ready","is_inferred","has_explicit_value"],"fullname":"conversions.prefix_conversions_string.SIUnit.kilo","name":"kilo","type":{".class":"Instance","args":[],"extra_attrs":null,"last_known_value":{".class":"LiteralType","fallback":"builtins.int","value":3},"type_ref":"builtins.int"}}},"mega":{".class":"SymbolTableNode","kind":"Mdef","node":{".class":"Var","flags":["is_initialized_in_class","is_final","is_ready","is_inferred","has_explicit_value"],"fullname":"conversions.prefix_conversions_string.SIUnit.mega","name":"mega","type":{".class":"Instance","args":[],"extra_attrs":null,"last_known_value":{".class":"LiteralType","fallback":"builtins.int","value":6},"type_ref":"builtins.int"}}},"micro":{".class":"SymbolTableNode","kind":"Mdef","node":{".class":"Var","flags":["is_initialized_in_class","is_final","is_ready","is_inferred","has_explicit_value"],"fullname":"conversions.prefix_conversions_string.SIUnit.micro","name":"micro","type":{".class":"Instance","args":[],"extra_attrs":null,"last_known_value":{".class":"LiteralType","fallback":"builtins.int","value":-6},"type_ref":"builtins.int"}}},"milli":{".class":"SymbolTableNode","kind":"Mdef","node":{".class":"Var","flags":["is_initialized_in_class","is_final","is_ready","is_inferred","has_explicit_value"],"fullname":"conversions.prefix_conversions_string.SIUnit.milli","name":"milli","type":{".class":"Instance","args":[],"extra_attrs":null,"last_known_value":{".class":"LiteralType","fallback":"builtins.int","value":-3},"type_ref":"builtins.int"}}},"nano":{".class":"SymbolTableNode","kind":"Mdef","node":{".class":"Var","flags":["is_initialized_in_class","is_final","is_ready","is_inferred","has_explicit_value"],"fullname":"conversions.prefix_conversions_string.SIUnit.nano","name":"nano","type":{".class":"Instance","args":[],"extra_attrs":null,"last_known_value":{".class":"LiteralType","fallback":"builtins.int","value":-9},"type_ref":"builtins.int"}}},"peta":{".class":"SymbolTableNode","kind":"Mdef","node":{".class":"Var","flags":["is_initialized_in_class","is_final","is_ready","is_inferred","has_explicit_value"],"fullname":"conversions.prefix_conversions_string.SIUnit.peta","name":"peta","type":{".class":"Instance","args":[],"extra_attrs":null,"last_known_value":{".class":"LiteralType","fallback":"builtins.int","value":15},"type_ref":"builtins.int"}}},"pico":{".class":"SymbolTableNode","kind":"Mdef","node":{".class":"Var","flags":["is_initialized_in_class","is_final","is_ready","is_inferred","has_explicit_value"],"fullname":"conversions.prefix_conversions_string.SIUnit.pico","name":"pico","type":{".class":"Instance","args":[],"extra_attrs":null,"last_known_value":{".class":"LiteralType","fallback":"builtins.int","value":-12},"type_ref":"builtins.int"}}},"tera":{".class":"SymbolTableNode","kind":"Mdef","node":{".class":"Var","flags":["is_initialized_in_class","is_final","is_ready","is_inferred","has_explicit_value"],"fullname":"conversions.prefix_conversions_string.SIUnit.tera","name":"tera","type":{".class":"Instance","args":[],"extra_attrs":null,"last_known_value":{".class":"LiteralType","fallback":"builtins.int","value":12},"type_ref":"builtins.int"}}},"yocto":{".class":"SymbolTableNode","kind":"Mdef","node":{".class":"Var","flags":["is_initialized_in_class","is_final","is_ready","is_inferred","has_explicit_value"],"fullname":"conversions.prefix_conversions_string.SIUnit.yocto","name":"yocto","type":{".class":"Instance","args":[],"extra_attrs":null,"last_known_value":{".class":"LiteralType","fallback":"builtins.int","value":-24},"type_ref":"builtins.int"}}},"yotta":{".class":"SymbolTableNode","kind":"Mdef","node":{".class":"Var","flags":["is_initialized_in_class","is_final","is_ready","is_inferred","has_explicit_value"],"fullname":"conversions.prefix_conversions_string.SIUnit.yotta","name":"yotta","type":{".class":"Instance","args":[],"extra_attrs":null,"last_known_value":{".class":"LiteralType","fallback":"builtins.int","value":24},"type_ref":"builtins.int"}}},"zepto":{".class":"SymbolTableNode","kind":"Mdef","node":{".class":"Var","flags":["is_initialized_in_class","is_final","is_ready","is_inferred","has_explicit_value"],"fullname":"conversions.prefix_conversions_string.SIUnit.zepto","name":"zepto","type":{".class":"Instance","args":[],"extra_attrs":null,"last_known_value":{".class":"LiteralType","fallback":"builtins.int","value":-21},"type_ref":"builtins.int"}}},"zetta":{".class":"SymbolTableNode","kind":"Mdef","node":{".class":"Var","flags":["is_initialized_in_class","is_final","is_ready","is_inferred","has_explicit_value"],"fullname":"conversions.prefix_conversions_string.SIUnit.zetta","name":"zetta","type":{".class":"Instance","args":[],"extra_attrs":null,"last_known_value":{".class":"LiteralType","fallback":"builtins.int","value":21},"type_ref":"builtins.int"}}}},"self_type":{".class":"TypeVarType","default":{".class":"AnyType","missing_import_name":null,"source_any":null,"type_of_any":4},"fullname":"conversions.prefix_conversions_string.SIUnit.Self","id":0,"name":"Self","namespace":"","upper_bound":"conversions.prefix_conversions_string.SIUnit","values":[],"variance":0},"slots":null,"tuple_type":null,"type_vars":[],"typeddict_type":null}},"T":{".class":"SymbolTableNode","kind":"Gdef","node":{".class":"TypeVarExpr","default":{".class":"AnyType","missing_import_name":null,"source_any":null,"type_of_any":4},"fullname":"conversions.prefix_conversions_string.T","name":"T","upper_bound":"enum.Enum","values":[],"variance":0}},"TypeVar":{".class":"SymbolTableNode","cross_ref":"typing.TypeVar","kind":"Gdef"},"__annotations__":{".class":"SymbolTableNode","kind":"Gdef","node":{".class":"Var","flags":["is_ready"],"fullname":"conversions.prefix_conversions_string.__annotations__","name":"__annotations__","type":{".class":"Instance","args":["builtins.str",{".class":"AnyType","missing_import_name":null,"source_any":null,"type_of_any":6}],"extra_attrs":null,"type_ref":"builtins.dict"}}},"__doc__":{".class":"SymbolTableNode","kind":"Gdef","node":{".class":"Var","flags":["is_ready"],"fullname":"conversions.prefix_conversions_string.__doc__","name":"__doc__","type":"builtins.str"}},"__file__":{".class":"SymbolTableNode","kind":"Gdef","node":{".class":"Var","flags":["is_ready"],"fullname":"conversions.prefix_conversions_string.__file__","name":"__file__","type":"builtins.str"}},"__name__":{".class":"SymbolTableNode","kind":"Gdef","node":{".class":"Var","flags":["is_ready"],"fullname":"conversions.prefix_conversions_string.__name__","name":"__name__","type":"builtins.str"}},"__package__":{".class":"SymbolTableNode","kind":"Gdef","node":{".class":"Var","flags":["is_ready"],"fullname":"conversions.prefix_conversions_string.__package__","name":"__package__","type":"builtins.str"}},"__spec__":{".class":"SymbolTableNode","kind":"Gdef","node":{".class":"Var","flags":["is_ready"],"fullname":"conversions.prefix_conversions_string.__spec__","name":"__spec__","type":"importlib.machinery.ModuleSpec"}},"add_binary_prefix":{".class":"SymbolTableNode","kind":"Gdef","node":{".class":"FuncDef","abstract_status":0,"arg_kinds":[0],"arg_names":["value"],"dataclass_transform_spec":null,"flags":[],"fullname":"conversions.prefix_conversions_string.add_binary_prefix","name":"add_binary_prefix","type":{".class":"CallableType","arg_kinds":[0],"arg_names":["value"],"arg_types":["builtins.float"],"bound_args":[],"def_extras":{"first_arg":null},"fallback":"builtins.function","from_concatenate":false,"implicit":false,"imprecise_arg_kinds":false,"is_ellipsis_args":false,"name":"add_binary_prefix","ret_type":"builtins.str","type_guard":null,"type_is":null,"unpack_kwargs":false,"variables":[]}}},"add_si_prefix":{".class":"SymbolTableNode","kind":"Gdef","node":{".class":"FuncDef","abstract_status":0,"arg_kinds":[0],"arg_names":["value"],"dataclass_transform_spec":null,"flags":[],"fullname":"conversions.prefix_conversions_string.add_si_prefix","name":"add_si_prefix","type":{".class":"CallableType","arg_kinds":[0],"arg_names":["value"],"arg_types":["builtins.float"],"bound_args":[],"def_extras":{"first_arg":null},"fallback":"builtins.function","from_concatenate":false,"implicit":false,"imprecise_arg_kinds":false,"is_ellipsis_args":false,"name":"add_si_prefix","ret_type":"builtins.str","type_guard":null,"type_is":null,"unpack_kwargs":false,"variables":[]}}},"annotations":{".class":"SymbolTableNode","cross_ref":"__future__.annotations","kind":"Gdef"},"doctest":{".class":"SymbolTableNode","cross_ref":"doctest","kind":"Gdef"},"unique":{".class":"SymbolTableNode","cross_ref":"enum.unique","kind":"Gdef"}},"path":"domains\\python-master\\Python-master\\conversions\\prefix_conversions_string.py"}
